Workbook

Sheet Dashboard
B2: JOB COSTING DASHBOARD
B3: Job Name: | E3: Job #:
B4: Client: | E4: Start Date:
B5: Address: | E5: End Date:
B6: Project Manager: | E6: Contract Amount:
B8: COST SUMMARY
B9: Category | C9: Estimated | D9: Actual | E9: Variance | F9: % of Budget | G9: Status
B10: Labor | D10: =Labor!G54 | E10: =C10-D10 | F10: =IF(C10=0,"",D10/C10) | G10: =IF(C10=0,"",IF(E10>=0,"✓ Under Budget","⚠ Over Budget"))
B11: Materials | D11: =Materials!G54 | E11: =C11-D11 | F11: =IF(C11=0,"",D11/C11) | G11: =IF(C11=0,"",IF(E11>=0,"✓ Under Budget","⚠ Over Budget"))
B12: Subcontractors | D12: ='Subs & Equipment'!F14 | E12: =C12-D12 | F12: =IF(C12=0,"",D12/C12) | G12: =IF(C12=0,"",IF(E12>=0,"✓ Under Budget","⚠ Over Budget"))
B13: Equipment | D13: ='Subs & Equipment'!N14 | E13: =C13-D13 | F13: =IF(C13=0,"",D13/C13) | G13: =IF(C13=0,"",IF(E13>=0,"✓ Under Budget","⚠ Over Budget"))
B14: Change Orders | D14: ='Change Orders'!E24 | E14: =C14-D14 | F14: =IF(C14=0,"",D14/C14) | G14: =IF(C14=0,"",IF(E14>=0,"✓ Under Budget","⚠ Over Budget"))
B15: TOTAL | C15: =SUM(C10:C14) | D15: =SUM(D10:D14) | E15: =C15-D15 | F15: =IF(C15=0,"",D15/C15)
B17: PROFIT / LOSS ANALYSIS
C18: Contract Amount | E18: =F6
C19: Total Costs | E19: =D15
C20: Gross Profit | E20: =E18-E19
C21: Profit Margin | E21: =IF(E18=0,"",E20/E18)

Sheet Labor
B2: LABOR TRACKING
B3: Date | C3: Employee | D3: Role | E3: Hours | F3: Rate | G3: Total | H3: Category | I3: Notes
G4: =IF(E4="","",E4*F4)
G5: =IF(E5="","",E5*F5)
G6: =IF(E6="","",E6*F6)
G7: =IF(E7="","",E7*F7)
G8: =IF(E8="","",E8*F8)
G9: =IF(E9="","",E9*F9)
G10: =IF(E10="","",E10*F10)
G11: =IF(E11="","",E11*F11)
G12: =IF(E12="","",E12*F12)
G13: =IF(E13="","",E13*F13)
G14: =IF(E14="","",E14*F14)
G15: =IF(E15="","",E15*F15)
... G53: =IF(E53="","",E53*F53)
B54: TOTAL LABOR COST | G54: =SUM(G4:G53)

Sheet Materials
B2: MATERIALS TRACKING
B3: Date | C3: Supplier | D3: Description | E3: Qty | F3: Unit Cost | G3: Total | H3: Receipt # | I3: Category
G4: =IF(E4="","",E4*F4)
G5: =IF(E5="","",E5*F5)
G6: =IF(E6="","",E6*F6)
G7: =IF(E7="","",E7*F7)
G8: =IF(E8="","",E8*F8)
G9: =IF(E9="","",E9*F9)
G10: =IF(E10="","",E10*F10)
G11: =IF(E11="","",E11*F11)
G12: =IF(E12="","",E12*F12)
G13: =IF(E13="","",E13*F13)
G14: =IF(E14="","",E14*F14)
G15: =IF(E15="","",E15*F15)
... G53: =IF(E53="","",E53*F53)
B54: TOTAL MATERIALS COST | G54: =SUM(G4:G53)

Sheet Subs & Equipment
B2: SUBCONTRACTORS | I2: EQUIPMENT RENTALS
B3: Date | C3: Name | D3: Scope of Work | E3: Quote | F3: Actual | G3: Variance | I3: Date | J3: Item | K3: Vendor | L3: Days | M3: Rate | N3: Total
G4: =IF(E4="","",E4-F4) | N4: =IF(L4="","",L4*M4)
G5: =IF(E5="","",E5-F5) | N5: =IF(L5="","",L5*M5)
G6: =IF(E6="","",E6-F6) | N6: =IF(L6="","",L6*M6)
G7: =IF(E7="","",E7-F7) | N7: =IF(L7="","",L7*M7)
G8: =IF(E8="","",E8-F8) | N8: =IF(L8="","",L8*M8)
G9: =IF(E9="","",E9-F9) | N9: =IF(L9="","",L9*M9)
G10: =IF(E10="","",E10-F10) | N10: =IF(L10="","",L10*M10)
G11: =IF(E11="","",E11-F11) | N11: =IF(L11="","",L11*M11)
G12: =IF(E12="","",E12-F12) | N12: =IF(L12="","",L12*M12)
G13: =IF(E13="","",E13-F13) | N13: =IF(L13="","",L13*M13)
B14: SUBCONTRACTOR TOTAL | F14: =SUM(F4:F13) | I14: EQUIPMENT TOTAL | N14: =SUM(N4:N13)

Sheet Change Orders
B2: CHANGE ORDERS
B3: CO # | C3: Date | D3: Description | E3: Amount | F3: Approved By | G3: Status
B24: TOTAL APPROVED CHANGE ORDERS | E24: =SUMIF(G4:G23,"Approved",E4:E23)
